{
  "projects": [
    {
      "id": "1481",
      "name": "teste de mensagem",
      "budget": "9000",
      "category": {
        "id": "4",
        "name": "Planejamento"
      },
      "services": [],
      "cost": 0
    },
    {
      "id": "d7fa",
      "name": "Teste de atualização",
      "budget": "7000",
      "category": {
        "id": "3",
        "name": "Design"
      },
      "services": [
        {
          "name": "implantação",
          "cost": "600",
          "description": "Implantar empresa",
          "id": "c66f17bf-7923-4232-b3f9-feaae65111ae"
        },
        {
          "name": "Scrum master",
          "cost": "1500",
          "description": "Vai gerenciar o projeto",
          "id": "8b694bcf-a02c-48ca-b113-9d680e7f167f"
        }
      ],
      "cost": 2100
    },
    {
      "id": "08fb",
      "name": "implantação",
      "budget": "9000",
      "category": {
        "id": "3",
        "name": "Design"
      },
      "services": [
        {
          "name": "Dev full",
          "cost": "300",
          "description": "Criar algo",
          "id": "a7e03bbb-9fbb-4cad-9390-7603f627765b"
        }
      ],
      "cost": 500
    },
    {
      "id": "905b",
      "name": "teste",
      "budget": "6000",
      "category": {
        "id": "1",
        "name": "Infra"
      },
      "cost": 0,
      "services": []
    }
  ],
  "categories": [
    {
      "id": "1",
      "name": "Infra"
    },
    {
      "id": "2",
      "name": "Desenvolvimento"
    },
    {
      "id": "3",
      "name": "Design"
    },
    {
      "id": "4",
      "name": "Planejamento"
    }
  ]
}